argsrun-0.0.2.dist-info/WHEEL
argsrun-0.0.2.dist-info/DESCRIPTION.rst
argsrun-0.0.2.dist-info/RECORD
argsrun-0.0.2.dist-info/METADATA
argsrun-0.0.2.dist-info/metadata.json
argsrun-0.0.2.dist-info/entry_points.txt
argsrun-0.0.2.dist-info/top_level.txt
argsrun/discover.py
argsrun/__init__.py
