Metadata-Version: 2.0
Name: argsrun
Version: 0.0.2
Summary: Simple tool for creating commands & sub-commands
Home-page: https://github.com/popravich/argsrun
Author: Alexey Popravka
Author-email: alexey.popravka@horsedevel.com
License: MIT
Platform: POSIX
Classifier: Development Status :: 3 - Alpha
Classifier: Environment :: Console
Classifier: Intended Audience :: Developers
Classifier: License :: OSI Approved :: MIT License
Classifier: Operating System :: POSIX
Classifier: Programming Language :: Python
Classifier: Programming Language :: Python :: 3
Classifier: Programming Language :: Python :: 3.3
Classifier: Programming Language :: Python :: 3.4
Classifier: Topic :: Software Development
Classifier: Topic :: Software Development :: Libraries
Classifier: Topic :: Utilities
